actinfrictionpy/__init__.py
actinfrictionpy/_version.py
actinfrictionpy/equations.py
actinfrictionpy/files.py
actinfrictionpy/plots.py
actinfrictionpy-1.0.0.dist-info/LICENSE.txt
actinfrictionpy-1.0.0.dist-info/METADATA
actinfrictionpy-1.0.0.dist-info/WHEEL
actinfrictionpy-1.0.0.dist-info/top_level.txt
actinfrictionpy-1.0.0.dist-info/RECORD
